qlc_midi_mapper/__main__.py
qlc_midi_mapper/__version__.py
qlc_midi_mapper/models.py
qlc_midi_mapper/workspace.py
qlc_midi_mapper/gui/app.py
qlc_midi_mapper/gui/base.py
qlc_midi_mapper/gui/events.py
qlc_midi_mapper/gui/files.py
qlc_midi_mapper/gui/layout.py
qlc_midi_mapper/gui/menu.py
qlc_midi_mapper-1.0.0.dist-info/METADATA
qlc_midi_mapper-1.0.0.dist-info/WHEEL
qlc_midi_mapper-1.0.0.dist-info/entry_points.txt
qlc_midi_mapper-1.0.0.dist-info/top_level.txt
qlc_midi_mapper-1.0.0.dist-info/RECORD
