Metadata-Version: 2.4
Name: qlc_midi_mapper
Version: 1.0.0
Summary: A python tool to easily map qlc buttons and midi.
Author-email: Rémi Giorno <remi.giorno@gmail.com>
Project-URL: Homepage, https://gitlab.com/remi.giorno/qlc_midi_mapper
Requires-Python: >=3.10
Requires-Dist: defusedxml
Requires-Dist: tkinterdnd2
Provides-Extra: test
Requires-Dist: pytest>=9.0.1; extra == "test"
